forgestripe/__init__.py
forgestripe/apps.py
forgestripe/models.py
forgestripe/settings.py
forgestripe/templatetags/__init__.py
forgestripe/templatetags/stripe.py
forgestripe/views.py
forge_stripe-0.1.1.dist-info/METADATA
forge_stripe-0.1.1.dist-info/WHEEL
forge_stripe-0.1.1.dist-info/RECORD
