Metadata-Version: 2.1
Name: forge-stripe
Version: 0.1.1
Summary: 
Author: Dave Gaeddert
Author-email: dave.gaeddert@dropseed.dev
Requires-Python: >=3.8,<4.0
Classifier: Programming Language :: Python :: 3
Classifier: Programming Language :: Python :: 3.8
Classifier: Programming Language :: Python :: 3.9
Classifier: Programming Language :: Python :: 3.10
Classifier: Programming Language :: Python :: 3.11
Classifier: Programming Language :: Python :: 3.12
Classifier: Programming Language :: Python :: 3.13
Requires-Dist: stripe (>=5.0.0,<6.0.0)
